pageable_mongo/__init__.py
pageable_mongo-0.1.0.dist-info/LICENSE.txt
pageable_mongo-0.1.0.dist-info/METADATA
pageable_mongo-0.1.0.dist-info/WHEEL
pageable_mongo-0.1.0.dist-info/top_level.txt
pageable_mongo-0.1.0.dist-info/RECORD
