Metadata-Version: 2.1
Name: pageable-mongo
Version: 0.1.0
Summary: Paging support for Mongo
Home-page: https://github.com/christophevg/pageable-mongo
Author: Christophe VG
License: MIT
Keywords: pageable mongo
Platform: UNKNOWN
Classifier: Programming Language :: Python :: 3
Classifier: Intended Audience :: Developers
Requires-Dist: pymongo (>=3.6)
